<?xml version="1.0" encoding="UTF-8" standalone="no"?>
<scene depth="1" desc="" eventsnippetid="264" extheight="960" extwidth="3264" extx="-32" exty="-32" format="2.1" gravx="-0.0" gravy="0.0" height="896" id="12" name="Desert of the Eyes" revision="" savecount="0" tiled="1" tileh="32" tilew="32" type="standard" width="3200">
    <layers>
        <layer color="100,168,234" id="0" name="Layer 0" order="0"/>
    </layers>
    <grad-bg b1="255" b2="255" g1="255" g2="255" r1="0" r2="0"/>
    <backgrounds/>
    <foregrounds/>
    <joints/>
    <regions/>
    <terrainRegions/>
    <actors>
        <actor a="0.0" aid="1" c="false" group="3" id="581" name="Star Coin 1" sx="1.0" sy="1.0" x="898" y="820" z="0"/>
        <actor a="0.0" aid="2" c="false" group="3" id="581" name="Star Coin 2" sx="1.0" sy="1.0" x="1394" y="623" z="0"/>
        <actor a="0.0" aid="3" c="false" group="3" id="581" name="Star Coin 3" sx="1.0" sy="1.0" x="1729" y="824" z="0"/>
    </actors>
    <snippets/>
    <terrain>
        <p pts="4,32.0,0.0,32.0,32.0,0.0,32.0,0.0,0.0" x="576.0" y="576.0"/>
        <p pts="4,0.0,32.0,0.0,0.0,64.0,0.0,64.0,32.0" x="448.0" y="576.0"/>
        <p pts="4,32.0,0.0,32.0,32.0,0.0,32.0,0.0,0.0" x="1472.0" y="672.0"/>
        <p pts="4,0.0,32.0,0.0,0.0,64.0,0.0,64.0,32.0" x="320.0" y="576.0"/>
        <p pts="4,32.0,32.0,32.0,0.0,0.0,0.0,0.0,32.0" x="1216.0" y="736.0"/>
        <p pts="4,32.0,0.0,32.0,32.0,0.0,32.0,0.0,0.0" x="1344.0" y="640.0"/>
        <p pts="4,0.0,0.0,128.0,0.0,128.0,224.0,0.0,224.0" x="544.0" y="256.0"/>
        <p pts="4,0.0,224.0,0.0,0.0,128.0,0.0,128.0,224.0" x="832.0" y="256.0"/>
        <p pts="4,32.0,0.0,32.0,32.0,0.0,32.0,0.0,0.0" x="704.0" y="576.0"/>
        <p pts="4,0.0,128.0,128.0,128.0,128.0,0.0,0.0,0.0" x="2656.0" y="256.0"/>
        <p pts="4,64.0,96.0,64.0,0.0,0.0,0.0,0.0,96.0" x="2176.0" y="416.0"/>
        <p pts="4,128.0,0.0,128.0,32.0,0.0,32.0,0.0,0.0" x="864.0" y="640.0"/>
        <p pts="4,0.0,32.0,0.0,0.0,64.0,0.0,64.0,32.0" x="2688.0" y="320.0"/>
        <p pts="4,32.0,0.0,32.0,32.0,0.0,32.0,0.0,0.0" x="1312.0" y="672.0"/>
        <p pts="4,0.0,0.0,0.0,96.0,64.0,96.0,64.0,0.0" x="1664.0" y="416.0"/>
        <p pts="4,0.0,0.0,128.0,0.0,128.0,256.0,0.0,256.0" x="2144.0" y="288.0"/>
        <p pts="4,0.0,32.0,64.0,32.0,64.0,0.0,0.0,0.0" x="576.0" y="288.0"/>
        <p pts="12,224.0,64.0,224.0,32.0,288.0,32.0,288.0,0.0,0.0,0.0,0.0,32.0,64.0,32.0,64.0,64.0,128.0,64.0,128.0,96.0,160.0,96.0,160.0,64.0" x="1600.0" y="768.0"/>
        <p pts="4,0.0,0.0,0.0,32.0,32.0,32.0,32.0,0.0" x="256.0" y="736.0"/>
        <p pts="4,64.0,0.0,0.0,0.0,0.0,64.0,64.0,64.0" x="864.0" y="384.0"/>
        <p pts="4,64.0,96.0,64.0,0.0,0.0,0.0,0.0,96.0" x="1280.0" y="352.0"/>
        <p pts="4,32.0,0.0,32.0,32.0,0.0,32.0,0.0,0.0" x="288.0" y="608.0"/>
        <p pts="34,2112.0,224.0,2208.0,224.0,2208.0,256.0,0.0,256.0,0.0,128.0,192.0,128.0,192.0,96.0,160.0,96.0,160.0,64.0,256.0,64.0,256.0,96.0,544.0,96.0,544.0,32.0,608.0,32.0,608.0,96.0,896.0,96.0,896.0,32.0,960.0,32.0,960.0,96.0,992.0,96.0,992.0,192.0,1440.0,192.0,1440.0,128.0,1472.0,128.0,1472.0,96.0,1504.0,96.0,1504.0,64.0,1536.0,64.0,1536.0,32.0,1888.0,32.0,1888.0,224.0,2080.0,224.0,2080.0,0.0,2112.0,0.0" x="992.0" y="640.0"/>
        <p pts="4,0.0,64.0,64.0,64.0,64.0,0.0,0.0,0.0" x="2176.0" y="320.0"/>
        <p pts="4,64.0,0.0,64.0,32.0,0.0,32.0,0.0,0.0" x="736.0" y="544.0"/>
        <p pts="48,640.0,32.0,608.0,32.0,608.0,0.0,672.0,0.0,672.0,32.0,736.0,32.0,736.0,64.0,704.0,64.0,704.0,160.0,896.0,160.0,896.0,288.0,0.0,288.0,0.0,128.0,32.0,128.0,32.0,96.0,64.0,96.0,64.0,64.0,96.0,64.0,96.0,32.0,160.0,32.0,160.0,64.0,192.0,64.0,192.0,96.0,224.0,96.0,224.0,128.0,256.0,128.0,256.0,96.0,352.0,96.0,352.0,64.0,448.0,64.0,448.0,96.0,416.0,96.0,416.0,160.0,448.0,160.0,448.0,128.0,480.0,128.0,480.0,96.0,512.0,96.0,512.0,64.0,576.0,64.0,576.0,96.0,608.0,96.0,608.0,128.0,640.0,128.0,640.0,160.0,672.0,160.0,672.0,64.0,640.0,64.0" x="0.0" y="608.0"/>
        <p pts="4,128.0,288.0,0.0,288.0,0.0,0.0,128.0,0.0" x="1248.0" y="192.0"/>
        <p pts="4,32.0,0.0,32.0,32.0,0.0,32.0,0.0,0.0" x="416.0" y="608.0"/>
        <p pts="4,0.0,32.0,0.0,0.0,128.0,0.0,128.0,32.0" x="736.0" y="704.0"/>
        <p pts="4,64.0,96.0,64.0,0.0,0.0,0.0,0.0,96.0" x="1280.0" y="224.0"/>
        <p pts="4,0.0,0.0,32.0,0.0,32.0,128.0,0.0,128.0" x="928.0" y="768.0"/>
        <p pts="4,0.0,32.0,0.0,0.0,128.0,0.0,128.0,32.0" x="992.0" y="704.0"/>
        <p pts="4,0.0,32.0,0.0,0.0,384.0,0.0,384.0,32.0" x="2016.0" y="768.0"/>
        <p pts="4,0.0,32.0,64.0,32.0,64.0,0.0,0.0,0.0" x="1664.0" y="352.0"/>
        <p pts="4,0.0,224.0,0.0,0.0,128.0,0.0,128.0,224.0" x="1632.0" y="320.0"/>
        <p pts="4,192.0,192.0,0.0,192.0,0.0,0.0,192.0,0.0" x="2624.0" y="224.0"/>
        <p pts="4,64.0,96.0,64.0,0.0,0.0,0.0,0.0,96.0" x="576.0" y="352.0"/>
        <p pts="4,32.0,0.0,32.0,32.0,0.0,32.0,0.0,0.0" x="1440.0" y="640.0"/>
        <p pts="4,0.0,64.0,64.0,64.0,64.0,0.0,0.0,0.0" x="864.0" y="288.0"/>
        <p pts="6,0.0,32.0,0.0,64.0,64.0,64.0,64.0,0.0,32.0,0.0,32.0,32.0" x="320.0" y="704.0"/>
    </terrain>
</scene>
